MANIFEST.in
setup.py
cpolymer/__init__.py
cpolymer/angle.py
cpolymer/bond.py
cpolymer/cell.py
cpolymer/constrain.py
cpolymer/create.py
cpolymer/lsimu.py
cpolymer/pair.py
cpolymer/polymer.py
cpolymer/proba.py
cpolymer/sortn.py
cpolymer/test-create.py
cpolymer/test-lsimu.py
cpolymer/test-polymer.py
cpolymer/test-proba.py
cpolymer/translate_cdf_cdc.py
cpolymer/utils.py
cpolymer.egg-info/PKG-INFO
cpolymer.egg-info/SOURCES.txt
cpolymer.egg-info/dependency_links.txt
cpolymer.egg-info/not-zip-safe
cpolymer.egg-info/top_level.txt
cpolymer/halley/__init__.py
cpolymer/halley/constrain.py
cpolymer/halley/vectors.py
cpolymer/template/basic.txt
cpolymer/template/basic_rest.txt
cpolymer/template/basic_rest.txt~
cpolymer/template/cg.txt
cpolymer/template/nucleus_init.txt
cpolymer/template/restart.txt