Metadata-Version: 1.0
Name: cpolymer
Version: 0.35
Summary: Creating initial configuration for polymer (to work with lammps)
Home-page: https://github.com/jeammimi/cpolymer
Author: Jean-michel Arbona
Author-email: jeanmichel.arbona@gmail.com
License: MIT
Platform: UNKNOWN
